{
  "meta": {
    "disclaimer": "Do not rely on openFDA to make decisions regarding medical care. While we make every effort to ensure that data is accurate, you should assume all results are unvalidated. We may limit or otherwise restrict your access to the API in line with our Terms of Service.",
    "terms": "https://open.fda.gov/terms/",
    "license": "https://open.fda.gov/license/",
    "last_updated": "2026-06-08",
    "results": {
      "skip": 0,
      "limit": 10,
      "total": 1
    }
  },
  "results": [
    {
      "third_party_flag": "N",
      "life_sustain_support_flag": "N",
      "gmp_exempt_flag": "N",
      "summary_malfunction_reporting": "Eligible",
      "product_code": "KIT",
      "openfda": {
        "k_number": [
          "K883451",
          "K850520",
          "K883496",
          "K821917",
          "K861886",
          "K852475",
          "K882790",
          "K882785",
          "K883450",
          "K883628",
          "K851605",
          "K820924",
          "K852288",
          "K810776",
          "K810770",
          "K851737",
          "K834136",
          "K850222",
          "K873016",
          "K882996",
          "K821915",
          "K881000",
          "K873019",
          "K850521",
          "K882856",
          "K883500",
          "K833391",
          "K883285",
          "K821913",
          "K812617",
          "K810780",
          "K820508",
          "K882857",
          "K833394",
          "K883627",
          "K872918",
          "K883364",
          "K831686",
          "K820930",
          "K883290",
          "K770764",
          "K883624",
          "K882853",
          "K863696",
          "K883629",
          "K883365",
          "K844288",
          "K850515",
          "K861885",
          "K832836",
          "K852568",
          "K882808",
          "K821912",
          "K882839",
          "K850886",
          "K882776",
          "K882992",
          "K873021",
          "K882789",
          "K882860",
          "K820917",
          "K883497",
          "K843863",
          "K882965",
          "K882838",
          "K883502",
          "K882859",
          "K883447",
          "K851604",
          "K845012",
          "K882774",
          "K883367",
          "K883631",
          "K883449",
          "K843086",
          "K883630",
          "K820926",
          "K855085",
          "K803041",
          "K842672",
          "K884573",
          "K832838",
          "K834116",
          "K861875",
          "K882782",
          "K832687",
          "K861873",
          "K832930",
          "K864396",
          "K882843",
          "K850225",
          "K883448",
          "K873093",
          "K871191",
          "K831685",
          "K861871",
          "K851608",
          "K841993",
          "K873090",
          "K883065",
          "K850525",
          "K832835",
          "K810774",
          "K882840",
          "K882773",
          "K882807",
          "K812885",
          "K870496",
          "K850233",
          "K884654",
          "K845013",
          "K834122",
          "K882841",
          "K833393",
          "K820916",
          "K850518",
          "K884572",
          "K882777",
          "K884574",
          "K882775",
          "K850921",
          "K882984",
          "K850091",
          "K882861",
          "K851862",
          "K833164",
          "K820919",
          "K882778",
          "K850522",
          "K882988",
          "K882852",
          "K870492",
          "K870529",
          "K873095",
          "K850517",
          "K883495",
          "K882990",
          "K873092",
          "K831519",
          "K882865",
          "K882985",
          "K850223",
          "K850516",
          "K882787",
          "K850237",
          "K810784",
          "K821916",
          "K882851",
          "K821911",
          "K850510",
          "K810783",
          "K821918",
          "K810773",
          "K882858",
          "K812820",
          "K882849",
          "K873026",
          "K882994",
          "K870488",
          "K873022",
          "K873084",
          "K873085",
          "K860786",
          "K810771",
          "K820495",
          "K883632",
          "K833168",
          "K820914",
          "K851738",
          "K873094",
          "K843043",
          "K870876",
          "K851863",
          "K854567",
          "K812531",
          "K850512",
          "K833163",
          "K820915",
          "K810768",
          "K882780",
          "K820920",
          "K882983",
          "K883287",
          "K883498",
          "K883363",
          "K882862",
          "K870481",
          "K883626",
          "K873014",
          "K871250",
          "K882866",
          "K850514",
          "K883368",
          "K832688",
          "K850228",
          "K820921",
          "K890701",
          "K883951",
          "K850523",
          "K834113",
          "K810767",
          "K833016",
          "K882991",
          "K850513",
          "K882989",
          "K873027",
          "K882842",
          "K882806",
          "K882863",
          "K843085",
          "K873018",
          "K850891",
          "K873091",
          "K870478",
          "K882987",
          "K833389",
          "K872465",
          "K850524",
          "K820925",
          "K860787",
          "K860623",
          "K883369",
          "K882993",
          "K850219",
          "K873017",
          "K850235",
          "K852602",
          "K883446",
          "K832690",
          "K884031",
          "K851609",
          "K882986",
          "K810781",
          "K820929",
          "K883370",
          "K883139",
          "K861887",
          "K850230",
          "K850511",
          "K882995",
          "K882864",
          "K882854",
          "K850526",
          "K873020",
          "K883682",
          "K861872",
          "K850519",
          "K832837",
          "K870479",
          "K850922",
          "K860282",
          "K873013",
          "K843045",
          "K883625",
          "K882997",
          "K861870",
          "K882837",
          "K850224",
          "K850679",
          "K832842",
          "K882788",
          "K883289",
          "K870494",
          "K850218",
          "K860788",
          "K860783",
          "K873028",
          "K832689",
          "K873024",
          "K870495",
          "K850236",
          "K850227",
          "K870498",
          "K861867",
          "K873025",
          "K840744",
          "K851607",
          "K810778",
          "K870497",
          "K850890",
          "K883362",
          "K892938",
          "K845014",
          "K883138",
          "K882844",
          "K870493",
          "K841744",
          "K870485",
          "K860785",
          "K870530",
          "K873023",
          "K832839",
          "K850234",
          "K890482",
          "K883286",
          "K850089",
          "K861874",
          "K832840",
          "K880999",
          "K870490",
          "K850092",
          "K873015",
          "K861868",
          "K850226",
          "K883288",
          "K870487",
          "K832841",
          "K870489",
          "K870499",
          "K850217",
          "K882781",
          "K882784",
          "K851606",
          "K883291",
          "K882855",
          "K883366",
          "K820922",
          "K833392",
          "K850537",
          "K831745",
          "K820931",
          "K850232",
          "K821919",
          "K870483",
          "K882847",
          "K842671",
          "K882848",
          "K861869",
          "K864740",
          "K883623",
          "K883141",
          "K843044",
          "K850990",
          "K852485",
          "K821914",
          "K850090",
          "K820918",
          "K882783",
          "K810769",
          "K842776",
          "K843864",
          "K850221",
          "K861996",
          "K883501",
          "K810772",
          "K842775",
          "K882786",
          "K883140",
          "K820509",
          "K890700",
          "K843862",
          "K833390",
          "K880691",
          "K883499",
          "K833165",
          "K882846",
          "K870451",
          "K850220",
          "K882779",
          "K883292",
          "K842002",
          "K850229",
          "K882845",
          "K883445",
          "K833169",
          "K882850",
          "K870480"
        ],
        "registration_number": [
          "3006236690",
          "3035387168",
          "3008496303",
          "3036495174",
          "3004107906",
          "1114298",
          "3013221738",
          "9614209",
          "3006158025",
          "3010512490",
          "3005182159",
          "3031092085",
          "3005182157",
          "3017716384",
          "3008624479",
          "3042175767",
          "3015715780",
          "1318354",
          "3039436068",
          "1048735",
          "1226230",
          "3005875593",
          "1123137",
          "3038430126",
          "2022379",
          "1528450",
          "3014588186"
        ],
        "fei_number": [
          "3006236690",
          "3035387168",
          "3008496303",
          "3036495174",
          "3004107906",
          "1114298",
          "3013221738",
          "3002806725",
          "1000123180",
          "3006158025",
          "3010512490",
          "3005182159",
          "3031092085",
          "3005182157",
          "3017716384",
          "3008624479",
          "3042175767",
          "3015715780",
          "1318354",
          "3039436068",
          "1048735",
          "3005875593",
          "1000122536",
          "3038430126",
          "2022379",
          "3002836339",
          "3014588186"
        ]
      },
      "review_panel": "PA",
      "medical_specialty": "HE",
      "device_name": "Media And Components, Synthetic Cell And Tissue Culture",
      "review_code": "",
      "unclassified_reason": "",
      "medical_specialty_description": "Hematology",
      "device_class": "1",
      "definition": "",
      "regulation_number": "864.2220",
      "implant_flag": "N",
      "submission_type_id": "4"
    }
  ]
}